{"total_products":74,"hash":14028083166117723774,"products":[{"product_id":"E476430-000","name":"Oversized Bicolor T-Shirt | Ringer","image_url":"https://image.uniqlo.com/UQ/ST3/id/imagesgoods/476430/item/idgoods_05_476430_3x4.jpg","base_price":"249000.0000","discounted_price":"199000.0000"},{"product_id":"E475366-000","name":"Oversized Bicolor T-Shirt | Raglan","image_url":"https://image.uniqlo.com/UQ/ST3/id/imagesgoods/475366/item/idgoods_03_475366_3x4.jpg","base_price":"249000.0000","discounted_price":"199000.0000"},{"product_id":"E467145-000","name":"DRY-EX T-Shirt","image_url":"https://image.uniqlo.com/UQ/ST3/AsianCommon/imagesgoods/467145/item/goods_01_467145_3x4.jpg","base_price":"249000.0000","discounted_price":"199000.0000"},{"product_id":"E477340-000","name":"AIRism Cotton Striped T-Shirt | Long Sleeve","image_url":"https://image.uniqlo.com/UQ/ST3/id/imagesgoods/477340/item/idgoods_00_477340_3x4.jpg","base_price":"299000.0000","discounted_price":"199000.0000"},{"product_id":"E473057-000","name":"AIRism Cotton T-Shirt | Striped Long Sleeve","image_url":"https://image.uniqlo.com/UQ/ST3/AsianCommon/imagesgoods/473057/item/goods_00_473057_3x4.jpg","base_price":"299000.0000","discounted_price":"199000.0000"},{"product_id":"E476216-000","name":"Crew Neck T-Shirt | 3/4 Sleeve","image_url":"https://image.uniqlo.com/UQ/ST3/id/imagesgoods/476216/item/idgoods_07_476216_3x4.jpg","base_price":"249000.0000","discounted_price":"199000.0000"},{"product_id":"E479034-000","name":"Manga Short Sleeve UT","image_url":"https://image.uniqlo.com/UQ/ST3/id/imagesgoods/479034/item/idgoods_00_479034_3x4.jpg","base_price":"199000.0000","discounted_price":"129000.0000"},{"product_id":"E479033-000","name":"Manga Short Sleeve UT","image_url":"https://image.uniqlo.com/UQ/ST3/id/imagesgoods/479033/item/idgoods_69_479033_3x4.jpg","base_price":"199000.0000","discounted_price":"129000.0000"},{"product_id":"E477529-000","name":"Tate Short Sleeve UT","image_url":"https://image.uniqlo.com/UQ/ST3/id/imagesgoods/477529/item/idgoods_00_477529_3x4.jpg","base_price":"199000.0000","discounted_price":"129000.0000"},{"product_id":"E477527-000","name":"Tate Short Sleeve UT","image_url":"https://image.uniqlo.com/UQ/ST3/id/imagesgoods/477527/item/idgoods_00_477527_3x4.jpg","base_price":"199000.0000","discounted_price":"129000.0000"},{"product_id":"E474456-000","name":"Tate Short Sleeve UT","image_url":"https://image.uniqlo.com/UQ/ST3/id/imagesgoods/474456/item/idgoods_09_474456_3x4.jpg","base_price":"199000.0000","discounted_price":"129000.0000"},{"product_id":"E478911-000","name":"Henri Matisse Short Sleeve UT","image_url":"https://image.uniqlo.com/UQ/ST3/id/imagesgoods/478911/item/idgoods_64_478911_3x4.jpg","base_price":"199000.0000","discounted_price":"129000.0000"},{"product_id":"E478910-000","name":"Henri Matisse Short Sleeve UT","image_url":"https://image.uniqlo.com/UQ/ST3/id/imagesgoods/478910/item/idgoods_00_478910_3x4.jpg","base_price":"199000.0000","discounted_price":"129000.0000"},{"product_id":"E478909-000","name":"Henri Matisse Short Sleeve UT","image_url":"https://image.uniqlo.com/UQ/ST3/id/imagesgoods/478909/item/idgoods_30_478909_3x4.jpg","base_price":"199000.0000","discounted_price":"129000.0000"},{"product_id":"E477812-000","name":"Peanuts Short Sleeve UT","image_url":"https://image.uniqlo.com/UQ/ST3/AsianCommon/imagesgoods/477812/item/goods_54_477812_3x4.jpg","base_price":"199000.0000","discounted_price":"129000.0000"},{"product_id":"E477811-000","name":"Peanuts Short Sleeve UT","image_url":"https://image.uniqlo.com/UQ/ST3/AsianCommon/imagesgoods/477811/item/goods_03_477811_3x4.jpg","base_price":"199000.0000","discounted_price":"129000.0000"},{"product_id":"E476350-000","name":"KAWS + Warhol Short Sleeve UT","image_url":"https://image.uniqlo.com/UQ/ST3/AsianCommon/imagesgoods/476350/item/goods_00_476350_3x4.jpg","base_price":"199000.0000","discounted_price":"99000.0000"},{"product_id":"E475381-000","name":"Half-Zip Sweatshirt","image_url":"https://image.uniqlo.com/UQ/ST3/id/imagesgoods/475381/item/idgoods_01_475381_3x4.jpg","base_price":"599000.0000","discounted_price":"399000.0000"},{"product_id":"E476217-000","name":"AIRism Cotton Polo Shirt","image_url":"https://image.uniqlo.com/UQ/ST3/id/imagesgoods/476217/item/idgoods_07_476217_3x4.jpg","base_price":"399000.0000","discounted_price":"299000.0000"},{"product_id":"E476017-000","name":"Broadcloth Shirt | Long Sleeve Checked","image_url":"https://image.uniqlo.com/UQ/ST3/id/imagesgoods/476017/item/idgoods_13_476017_3x4.jpg","base_price":"399000.0000","discounted_price":"299000.0000"},{"product_id":"E476016-000","name":"Broadcloth Shirt | Long Sleeve Checked","image_url":"https://image.uniqlo.com/UQ/ST3/id/imagesgoods/476016/item/idgoods_64_476016_3x4.jpg","base_price":"399000.0000","discounted_price":"299000.0000"},{"product_id":"E479644-000","name":"Chambray Over Shirt | Long Sleeve","image_url":"https://image.uniqlo.com/UQ/ST3/id/imagesgoods/479644/item/idgoods_61_479644_3x4.jpg","base_price":"499000.0000","discounted_price":"399000.0000"},{"product_id":"E476008-000","name":"Twill Overshirt | Long Sleeve","image_url":"https://image.uniqlo.com/UQ/ST3/id/imagesgoods/476008/item/idgoods_32_476008_3x4.jpg","base_price":"499000.0000","discounted_price":"399000.0000"},{"product_id":"E478977-000","name":"Flannel Shirt Long Sleeve","image_url":"https://image.uniqlo.com/UQ/ST3/id/imagesgoods/478977/item/idgoods_43_478977_3x4.jpg","base_price":"399000.0000","discounted_price":"299000.0000"},{"product_id":"E478930-000","name":"Flannel Shirt Long Sleeve","image_url":"https://image.uniqlo.com/UQ/ST3/id/imagesgoods/478930/item/idgoods_55_478930_3x4.jpg","base_price":"399000.0000","discounted_price":"299000.0000"},{"product_id":"E477806-000","name":"Flannel Shirt Long Sleeve","image_url":"https://image.uniqlo.com/UQ/ST3/AsianCommon/imagesgoods/477806/item/goods_04_477806_3x4.jpg","base_price":"399000.0000","discounted_price":"299000.0000"},{"product_id":"E470192-000","name":"Flannel Shirt | Long Sleeve Checked","image_url":"https://image.uniqlo.com/UQ/ST3/id/imagesgoods/470192/item/idgoods_03_470192_3x4.jpg","base_price":"399000.0000","discounted_price":"299000.0000"},{"product_id":"E476243-000","name":"Long Oversized Shirt | Long Sleeve","image_url":"https://image.uniqlo.com/UQ/ST3/id/imagesgoods/476243/item/idgoods_05_476243_3x4.jpg","base_price":"599000.0000","discounted_price":"399000.0000"},{"product_id":"E473064-000","name":"Modal Cotton Stand Collar Shirt | Short Sleeve","image_url":"https://image.uniqlo.com/UQ/ST3/id/imagesgoods/473064/item/idgoods_00_473064_3x4.jpg","base_price":"299000.0000","discounted_price":"199000.0000"},{"product_id":"E468914-000","name":"Modal Cotton Stand Collar Shirt | Short Sleeve","image_url":"https://image.uniqlo.com/UQ/ST3/AsianCommon/imagesgoods/468914/item/goods_00_468914_3x4.jpg","base_price":"299000.0000","discounted_price":"199000.0000"},{"product_id":"E476245-000","name":"Utility Oversized Shirt | Short Sleeve","image_url":"https://image.uniqlo.com/UQ/ST3/id/imagesgoods/476245/item/idgoods_09_476245_3x4.jpg","base_price":"499000.0000","discounted_price":"399000.0000"},{"product_id":"E474517-000","name":"Dry Non Iron Jersey Shirt | Short Sleeve","image_url":"https://image.uniqlo.com/UQ/ST3/AsianCommon/imagesgoods/474517/item/goods_61_474517_3x4.jpg","base_price":"399000.0000","discounted_price":"299000.0000"},{"product_id":"E474516-000","name":"Dry Non Iron Jersey Shirt | Short Sleeve","image_url":"https://image.uniqlo.com/UQ/ST3/AsianCommon/imagesgoods/474516/item/goods_70_474516_3x4.jpg","base_price":"399000.0000","discounted_price":"299000.0000"},{"product_id":"E474515-000","name":"Dry Non Iron Jersey Shirt | Short Sleeve","image_url":"https://image.uniqlo.com/UQ/ST3/AsianCommon/imagesgoods/474515/item/goods_68_474515_3x4.jpg","base_price":"399000.0000","discounted_price":"299000.0000"},{"product_id":"E467509-000","name":"Dry Non Iron Jersey Shirt | Short Sleeve","image_url":"https://image.uniqlo.com/UQ/ST3/AsianCommon/imagesgoods/467509/item/goods_63_467509_3x4.jpg","base_price":"399000.0000","discounted_price":"299000.0000"},{"product_id":"E455967-000","name":"Dry Non Iron Jersey Shirt | Short Sleeve","image_url":"https://image.uniqlo.com/UQ/ST3/AsianCommon/imagesgoods/455967/item/goods_00_455967_3x4.jpg","base_price":"399000.0000","discounted_price":"299000.0000"},{"product_id":"E476144-000","name":"Ultra Stretch Active Track Jacket (Matching Set)","image_url":"https://image.uniqlo.com/UQ/ST3/id/imagesgoods/476144/item/idgoods_04_476144_3x4.jpg","base_price":"499000.0000","discounted_price":"399000.0000"},{"product_id":"E475631-000","name":"Hooded Blouson","image_url":"https://image.uniqlo.com/UQ/ST3/id/imagesgoods/475631/item/idgoods_05_475631_3x4.jpg","base_price":"899000.0000","discounted_price":"699000.0000"},{"product_id":"E476196-000","name":"Light Weight Stand Blouson","image_url":"https://image.uniqlo.com/UQ/ST3/id/imagesgoods/476196/item/idgoods_25_476196_3x4.jpg","base_price":"999000.0000","discounted_price":"699000.0000"},{"product_id":"E475403-000","name":"Cotton Short Blouson","image_url":"https://image.uniqlo.com/UQ/ST3/id/imagesgoods/475403/item/idgoods_09_475403_3x4.jpg","base_price":"999000.0000","discounted_price":"899000.0000"},{"product_id":"E475039-000","name":"Ultra Stretch Jacket","image_url":"https://image.uniqlo.com/UQ/ST3/id/imagesgoods/475039/item/idgoods_08_475039_3x4.jpg","base_price":"999000.0000","discounted_price":"599000.0000"},{"product_id":"E476645-000","name":"Work Jacket","image_url":"https://image.uniqlo.com/UQ/ST3/id/imagesgoods/476645/item/idgoods_09_476645_3x4.jpg","base_price":"999000.0000","discounted_price":"699000.0000"},{"product_id":"E475404-000","name":"Miracle Air Jacket","image_url":"https://image.uniqlo.com/UQ/ST3/id/imagesgoods/475404/item/idgoods_01_475404_3x4.jpg","base_price":"899000.0000","discounted_price":"699000.0000"},{"product_id":"E476187-000","name":"Knitted Vest","image_url":"https://image.uniqlo.com/UQ/ST3/id/imagesgoods/476187/item/idgoods_09_476187_3x4.jpg","base_price":"499000.0000","discounted_price":"399000.0000"},{"product_id":"E475402-000","name":"BLOCKTECH Single Breasted Coat","image_url":"https://image.uniqlo.com/UQ/ST3/id/imagesgoods/475402/item/idgoods_09_475402_3x4.jpg","base_price":"1690000.0000","discounted_price":"1290000.0000"},{"product_id":"E475634-000","name":"Oversized Single Breasted Coat","image_url":"https://image.uniqlo.com/UQ/ST3/id/imagesgoods/475634/item/idgoods_07_475634_3x4.jpg","base_price":"1490000.0000","discounted_price":"999000.0000"},{"product_id":"E476177-000","name":"Crew Neck Sweater | Short Sleeve","image_url":"https://image.uniqlo.com/UQ/ST3/id/imagesgoods/476177/item/idgoods_09_476177_3x4.jpg","base_price":"499000.0000","discounted_price":"299000.0000"},{"product_id":"E475295-000","name":"Waffle V Neck Sweater","image_url":"https://image.uniqlo.com/UQ/ST3/id/imagesgoods/475295/item/idgoods_10_475295_3x4.jpg","base_price":"599000.0000","discounted_price":"499000.0000"},{"product_id":"E476179-000","name":"Crew Neck Sweater | Long Sleeve","image_url":"https://image.uniqlo.com/UQ/ST3/id/imagesgoods/476179/item/idgoods_09_476179_3x4.jpg","base_price":"499000.0000","discounted_price":"299000.0000"},{"product_id":"E475596-000","name":"Pleated Wide Pants","image_url":"https://image.uniqlo.com/UQ/ST3/id/imagesgoods/475596/item/idgoods_02_475596_3x4.jpg","base_price":"699000.0000","discounted_price":"599000.0000"},{"product_id":"E470549-000","name":"Wide Fit Chino Pants","image_url":"https://image.uniqlo.com/UQ/ST3/id/imagesgoods/470549/item/idgoods_07_470549_3x4.jpg","base_price":"599000.0000","discounted_price":"499000.0000"},{"product_id":"E470635-000","name":"Wide Fit Half Pants","image_url":"https://image.uniqlo.com/UQ/ST3/id/imagesgoods/470635/item/idgoods_09_470635_3x4.jpg","base_price":"599000.0000","discounted_price":"399000.0000"},{"product_id":"E476193-000","name":"Wide Fit Cargo Pants","image_url":"https://image.uniqlo.com/UQ/ST3/id/imagesgoods/476193/item/idgoods_09_476193_3x4.jpg","base_price":"599000.0000","discounted_price":"499000.0000"},{"product_id":"E475601-000","name":"Easy Work Pants","image_url":"https://image.uniqlo.com/UQ/ST3/id/imagesgoods/475601/item/idgoods_09_475601_3x4.jpg","base_price":"699000.0000","discounted_price":"599000.0000"},{"product_id":"E475385-000","name":"Ultra Stretch Active Track Pants (Matching Set)","image_url":"https://image.uniqlo.com/UQ/ST3/id/imagesgoods/475385/item/idgoods_04_475385_3x4.jpg","base_price":"399000.0000","discounted_price":"199000.0000"},{"product_id":"E476214-000","name":"Light Weight Wide Sweat Pants","image_url":"https://image.uniqlo.com/UQ/ST3/id/imagesgoods/476214/item/idgoods_07_476214_3x4.jpg","base_price":"599000.0000","discounted_price":"499000.0000"},{"product_id":"E470619-000","name":"Chino Shorts","image_url":"https://image.uniqlo.com/UQ/ST3/id/imagesgoods/470619/item/idgoods_01_470619_3x4.jpg","base_price":"399000.0000","discounted_price":"299000.0000"},{"product_id":"E476224-000","name":"DRY-EX Shorts","image_url":"https://image.uniqlo.com/UQ/ST3/id/imagesgoods/476224/item/idgoods_07_476224_3x4.jpg","base_price":"399000.0000","discounted_price":"299000.0000"},{"product_id":"E470625-000","name":"Stretch Slim Fit Shorts | Print","image_url":"https://image.uniqlo.com/UQ/ST3/id/imagesgoods/470625/item/idgoods_09_470625_3x4.jpg","base_price":"399000.0000","discounted_price":"299000.0000"},{"product_id":"E476195-000","name":"Wide Fit Cargo Half Pants","image_url":"https://image.uniqlo.com/UQ/ST3/id/imagesgoods/476195/item/idgoods_25_476195_3x4.jpg","base_price":"599000.0000","discounted_price":"299000.0000"},{"product_id":"E476194-000","name":"Wide Fit Cargo Shorts","image_url":"https://image.uniqlo.com/UQ/ST3/id/imagesgoods/476194/item/idgoods_09_476194_3x4.jpg","base_price":"599000.0000","discounted_price":"299000.0000"},{"product_id":"E470633-000","name":"Cargo Shorts","image_url":"https://image.uniqlo.com/UQ/ST3/id/imagesgoods/470633/item/idgoods_09_470633_3x4.jpg","base_price":"399000.0000","discounted_price":"299000.0000"},{"product_id":"E455900-000","name":"Stretch Easy Shorts (Chambray)","image_url":"https://image.uniqlo.com/UQ/ST3/AsianCommon/imagesgoods/455900/item/goods_07_455900_3x4.jpg","base_price":"299000.0000","discounted_price":"199000.0000"},{"product_id":"E477657-000","name":"Washed Jersey Easy Shorts","image_url":"https://image.uniqlo.com/UQ/ST3/AsianCommon/imagesgoods/477657/item/goods_08_477657_3x4.jpg","base_price":"299000.0000","discounted_price":"199000.0000"},{"product_id":"E466679-000","name":"Socks | Checked","image_url":"https://image.uniqlo.com/UQ/ST3/AsianCommon/imagesgoods/466679/item/goods_03_466679_3x4.jpg","base_price":"59000.0000","discounted_price":"39000.0000"},{"product_id":"E477730-000","name":"Half Socks | Rib","image_url":"https://image.uniqlo.com/UQ/ST3/AsianCommon/imagesgoods/477730/item/goods_03_477730_3x4.jpg","base_price":"59000.0000","discounted_price":"39000.0000"},{"product_id":"E466710-000","name":"Half Socks","image_url":"https://image.uniqlo.com/UQ/ST3/AsianCommon/imagesgoods/466710/item/goods_17_466710_3x4.jpg","base_price":"59000.0000","discounted_price":"39000.0000"},{"product_id":"E478903-000","name":"Andy Warhol Socks","image_url":"https://image.uniqlo.com/UQ/ST3/AsianCommon/imagesgoods/478903/item/goods_02_478903_3x4.jpg","base_price":"59000.0000","discounted_price":"39000.0000"},{"product_id":"E478896-000","name":"Andy Warhol Socks","image_url":"https://image.uniqlo.com/UQ/ST3/AsianCommon/imagesgoods/478896/item/goods_55_478896_3x4.jpg","base_price":"59000.0000","discounted_price":"39000.0000"},{"product_id":"E476379-000","name":"Round Mini Shoulder Bag | Pattern","image_url":"https://image.uniqlo.com/UQ/ST3/AsianCommon/imagesgoods/476379/item/goods_09_476379_3x4.jpg","base_price":"199000.0000","discounted_price":"129000.0000"},{"product_id":"E474149-000","name":"Round Shoulder Bag | Mesh","image_url":"https://image.uniqlo.com/UQ/ST3/AsianCommon/imagesgoods/474149/item/goods_00_474149_3x4.jpg","base_price":"299000.0000","discounted_price":"129000.0000"},{"product_id":"E475133-000","name":"Sunglasses | Boston Combination","image_url":"https://image.uniqlo.com/UQ/ST3/AsianCommon/imagesgoods/475133/item/goods_07_475133_3x4.jpg","base_price":"299000.0000","discounted_price":"129000.0000"},{"product_id":"E475513-000","name":"Slide Sandals","image_url":"https://image.uniqlo.com/UQ/ST3/AsianCommon/imagesgoods/475513/item/goods_09_475513_3x4.jpg","base_price":"599000.0000","discounted_price":"499000.0000"},{"product_id":"E475752-000","name":"KAWS + Warhol Art Book","image_url":"https://image.uniqlo.com/UQ/ST3/AsianCommon/imagesgoods/475752/item/goods_99_475752_3x4.jpg","base_price":"999000.0000","discounted_price":"299000.0000"}],"fetched_at":"2025-05-05T01:22:26.626142074Z"}